photoResizer/__init__.py
photoResizer/__main__.py
photoResizer/cli.py
photoResizer/config.py
photoResizer/resizer.py
photoResizer/settings.yaml
photoResizer-0.2.3.dist-info/LICENSE
photoResizer-0.2.3.dist-info/METADATA
photoResizer-0.2.3.dist-info/WHEEL
photoResizer-0.2.3.dist-info/entry_points.txt
photoResizer-0.2.3.dist-info/top_level.txt
photoResizer-0.2.3.dist-info/RECORD
