Metadata-Version: 2.1
Name: photoResizer
Version: 0.2.3
Summary: Photo Resizer, used mainly for Id cards and other documents.
Author-email: François GUÉRIN <frague59@gmail.com>
License: MIT
Project-URL: Homepage, https://gitlab.com/frague59/resize
Classifier: Development Status :: 3 - Alpha
Classifier: Programming Language :: Python :: 3
Classifier: Environment :: Console
Classifier: Intended Audience :: Developers
Classifier: Intended Audience :: End Users/Desktop
Classifier: Intended Audience :: Information Technology
Classifier: Intended Audience :: System Administrators
Classifier: License :: OSI Approved :: MIT License
Classifier: Operating System :: POSIX :: Linux
Classifier: Programming Language :: Python
Classifier: Programming Language :: Python :: 3.7
Classifier: Programming Language :: Python :: 3.8
Classifier: Programming Language :: Python :: 3.8
Classifier: Programming Language :: Python :: 3.10
Classifier: Programming Language :: Python :: 3.11
Classifier: Topic :: Multimedia :: Graphics
Classifier: Topic :: Utilities
License-File: LICENSE
Requires-Dist: click (~=8.0)
Requires-Dist: Willow (~=1.4)
Requires-Dist: Pillow (~=9.4)
Requires-Dist: pyYAML (~=6.0)
Requires-Dist: types-YAML
Provides-Extra: opencv
Requires-Dist: opencv-python ; extra == 'opencv'
Requires-Dist: opencv-contrib-python ; extra == 'opencv'
